Metadata-Version: 2.1
Name: money-To-words-Converter
Version: 1.1
Summary: convert int numbers (money , price ...) to words
Home-page: https://github.com/zzainoo/money-to-words
Author: zain alabdeen albaghdadi
Author-email: ta99kr@gmail.com
License: MIT
Platform: UNKNOWN
